speedupper/__init__.py
speedupper/lang.py
speedupper-0.1.0.dist-info/licenses/LICENSE
speedupper-0.1.0.dist-info/WHEEL
speedupper-0.1.0.dist-info/METADATA
speedupper-0.1.0.dist-info/RECORD
