Metadata-Version: 2.4
Name: speedupper
Version: 0.1.0
Summary: Simple FPS booster for Python loops
Requires-Python: >=3.7
License-File: LICENSE
